{"scene": "FloorPlan11", "agent": {"position": {"x": -2.5, "y": 0.9009991884231567, "z": -0.25}, "rotation": {"x": -0.0, "y": 0.9905075430870056, "z": 0.0, "cameraHorizon": -0.0}}, "objects": [{"objectName": "Cabinet_49427a4b", "rotation": {"x": -0.0, "y": 180.0, "z": -0.0}, "position": {"x": -0.19380000233650208, "y": 1.6881999969482422, "z": -1.648900032043457}, "type": "Cabinet", "is_goal_object": false}, {"objectName": "StoveBurner_9217cc15", "rotation": {"x": -0.0, "y": 180.00006103515625, "z": 0.0}, "position": {"x": 1.3609999418258667, "y": 0.9576473832130432, "z": 0.2939999997615814}, "type": "StoveBurner", "is_goal_object": false}, {"objectName": "Drawer_81ee8889", "rotation": {"x": -0.0, "y": 0.0, "z": 0.0}, "position": {"x": 0.4999999403953552, "y": 0.7924999594688416, "z": 0.296999990940094}, "type": "Drawer", "is_goal_object": false}, {"objectName": "Cabinet_a310425d", "rotation": {"x": -0.0, "y": 180.0, "z": -0.0}, "position": {"x": 0.09560000151395798, "y": 0.4009999930858612, "z": -1.3522000312805176}, "type": "Cabinet", "is_goal_object": false}, {"objectName": "Sink_673d1485", "rotation": {"x": -0.0, "y": 270.0, "z": 0.0}, "position": {"x": 0.71110999584198, "y": 0.817799985408783, "z": -1.7726999521255493}, "type": "Sink", "is_goal_object": false}, {"objectName": "CounterTop_190e10e4", "rotation": {"x": -0.0, "y": 0.0, "z": 0.0}, "position": {"x": 0.2809999883174896, "y": 0.9477999806404114, "z": 0.45809999108314514}, "type": "CounterTop", "is_goal_object": false}, {"objectName": "CounterTop_025bcfda", "rotation": {"x": -0.0, "y": 0.0, "z": 0.0}, "position": {"x": -0.6809999942779541, "y": 0.9477999806404114, "z": -1.6548000574111938}, "type": "CounterTop", "is_goal_object": false}, {"objectName": "Drawer_100dce28", "rotation": {"x": -0.0, "y": 0.0, "z": 0.0}, "position": {"x": 1.8250001668930054, "y": 0.7924999594688416, "z": 0.296999990940094}, "type": "Drawer", "is_goal_object": false}, {"objectName": "StoveBurner_84912640", "rotation": {"x": -0.0, "y": 269.9999084472656, "z": 0.0}, "position": {"x": 1.007099986076355, "y": 0.9576473832130432, "z": 0.5616999864578247}, "type": "StoveBurner", "is_goal_object": false}, {"objectName": "Drawer_a82c860b", "rotation": {"x": -0.0, "y": 0.0, "z": 0.0}, "position": {"x": -0.15000003576278687, "y": 0.7924999594688416, "z": -1.496999979019165}, "type": "Drawer", "is_goal_object": false}, {"objectName": "Drawer_eca7b585", "rotation": {"x": -0.0, "y": 0.0, "z": 0.0}, "position": {"x": -0.5863999724388123, "y": 0.7924999594688416, "z": -1.496999979019165}, "type": "Drawer", "is_goal_object": false}, {"objectName": "StoveBurner_dc457212", "rotation": {"x": -0.0, "y": 269.9999084472656, "z": 0.0}, "position": {"x": 1.3609999418258667, "y": 0.9576473832130432, "z": 0.5616999864578247}, "type": "StoveBurner", "is_goal_object": false}, {"objectName": "Drawer_2a559db7", "rotation": {"x": -0.0, "y": 0.0, "z": 0.0}, "position": {"x": 0.024999916553497314, "y": 0.7924999594688416, "z": 0.296999990940094}, "type": "Drawer", "is_goal_object": false}, {"objectName": "Cabinet_e814d981", "rotation": {"x": -0.0, "y": 180.0, "z": -0.0}, "position": {"x": 1.0799000263214111, "y": 0.4009000062942505, "z": -1.3495999574661255}, "type": "Cabinet", "is_goal_object": false}, {"objectName": "Cabinet_9efc2880", "rotation": {"x": -0.0, "y": 0.0, "z": 0.0}, "position": {"x": 1.6699999570846558, "y": 0.4025000333786011, "z": 0.1510000228881836}, "type": "Cabinet", "is_goal_object": false}, {"objectName": "Cabinet_2a148a75", "rotation": {"x": -0.0, "y": 0.0, "z": 0.0}, "position": {"x": 0.055000003427267075, "y": 0.4025000333786011, "z": -1.3510000705718994}, "type": "Cabinet", "is_goal_object": false}, {"objectName": "Cabinet_f81056bc", "rotation": {"x": -0.0, "y": 0.0, "z": 0.0}, "position": {"x": -0.18000012636184692, "y": 0.4025000333786011, "z": 0.1510000228881836}, "type": "Cabinet", "is_goal_object": false}, {"objectName": "Cabinet_99a05e0f", "rotation": {"x": -0.0, "y": 0.0, "z": 0.0}, "position": {"x": 0.7299999594688416, "y": 0.4025000333786011, "z": 0.1510000228881836}, "type": "Cabinet", "is_goal_object": false}, {"objectName": "StoveBurner_0dfa5b16", "rotation": {"x": -0.0, "y": 180.00006103515625, "z": 0.0}, "position": {"x": 1.007099986076355, "y": 0.9576473832130432, "z": 0.2937999963760376}, "type": "StoveBurner", "is_goal_object": false}, {"objectName": "Drawer_1000af13", "rotation": {"x": -0.0, "y": 0.0, "z": 0.0}, "position": {"x": -1.100000023841858, "y": 0.7924999594688416, "z": -1.496999979019165}, "type": "Drawer", "is_goal_object": false}, {"objectName": "Cabinet_58af87f2", "rotation": {"x": -0.0, "y": 0.0, "z": 0.0}, "position": {"x": -0.39649999141693115, "y": 0.4025000333786011, "z": -1.3510000705718994}, "type": "Cabinet", "is_goal_object": false}, {"objectName": "CounterTop_14eed47b", "rotation": {"x": -0.0, "y": 0.0, "z": 0.0}, "position": {"x": 1.7762999534606934, "y": 0.9477999806404114, "z": 0.45809999108314514}, "type": "CounterTop", "is_goal_object": false}, {"objectName": "Cabinet_7e42db0c", "rotation": {"x": -0.0, "y": 180.0, "z": -0.0}, "position": {"x": 1.9745999574661255, "y": 1.6881999969482422, "z": -1.648900032043457}, "type": "Cabinet", "is_goal_object": false}, {"objectName": "Floor_47ab48cf", "rotation": {"x": -0.0, "y": 0.0, "z": 0.0}, "position": {"x": 0.0, "y": 0.0, "z": 0.0}, "type": "Floor", "is_goal_object": false}, {"objectName": "Cabinet_c768dea8", "rotation": {"x": -0.0, "y": 180.0, "z": -0.0}, "position": {"x": -0.820900022983551, "y": 0.4009000062942505, "z": -1.3495999574661255}, "type": "Cabinet", "is_goal_object": false}, {"objectName": "Bread_512715d9", "rotation": {"x": -9.716881322674453e-06, "y": 9.136904282058822e-07, "z": 4.723586971522309e-05}, "position": {"x": -0.09697654098272324, "y": 0.9787496328353882, "z": 0.6238617300987244}, "type": "Bread", "is_goal_object": false}, {"objectName": "Knife_4d6026ce", "rotation": {"x": 0.00018612266285344958, "y": 87.47071075439453, "z": 89.99781036376953}, "position": {"x": -2.485067129135132, "y": 0.9491391181945801, "z": 0.6137039661407471}, "type": "Knife", "is_goal_object": true}, {"objectName": "Toaster_b62953d2", "rotation": {"x": 3.7672751204809174e-05, "y": 180.00001525878906, "z": 5.148718992131762e-05}, "position": {"x": 0.3050002455711365, "y": 0.8999999761581421, "z": 0.5529998540878296}, "type": "Toaster", "is_goal_object": false}, {"objectName": "Fork_f22e1984", "rotation": {"x": 0.2926432192325592, "y": 89.97882843017578, "z": 359.87677001953125}, "position": {"x": -2.369650363922119, "y": 0.9440963864326477, "z": 0.678713321685791}, "type": "Fork", "is_goal_object": false}, {"objectName": "Bowl_cbf69908", "rotation": {"x": 0.007983583956956863, "y": -0.0003801044076681137, "z": 0.000988500309176743}, "position": {"x": 1.6583560705184937, "y": 0.9037989377975464, "z": -1.4890366792678833}, "type": "Bowl", "is_goal_object": false}, {"objectName": "Kettle_7bf41620", "rotation": {"x": 0.0001481298531871289, "y": 4.395202495288686e-07, "z": 0.00011395615729270503}, "position": {"x": -0.09697642922401428, "y": 0.9043798446655273, "z": 0.3752191364765167}, "type": "Kettle", "is_goal_object": false}, {"objectName": "Cup_3af18e08", "rotation": {"x": 0.001638305839151144, "y": 0.00020898436196148396, "z": 359.993896484375}, "position": {"x": 0.6970919966697693, "y": 0.9000813364982605, "z": 0.20945733785629272}, "type": "Cup", "is_goal_object": false}, {"objectName": "SoapBottle_ee5263e7", "rotation": {"x": 2.7380153824196896e-06, "y": 1.721223452477716e-05, "z": 7.780054147588089e-06}, "position": {"x": 1.6630017757415771, "y": 0.899918794631958, "z": 0.6238619685173035}, "type": "SoapBottle", "is_goal_object": false}, {"objectName": "Plate_cce9e8b3", "rotation": {"x": 0.0003077167202718556, "y": 1.1765319868572988e-05, "z": 1.2308312761888374e-05}, "position": {"x": 1.8461343050003052, "y": 0.9001826047897339, "z": 0.2923382818698883}, "type": "Plate", "is_goal_object": false}, {"objectName": "LightSwitch_ac3cde2b", "rotation": {"x": -0.0, "y": 90.0, "z": -0.0}, "position": {"x": -2.756999969482422, "y": 1.3070000410079956, "z": -0.9879999756813049}, "type": "LightSwitch", "is_goal_object": false}, {"objectName": "Pot_40ca97b1", "rotation": {"x": -8.840358350425959e-05, "y": -1.9176939531462267e-05, "z": -0.00019596588390413672}, "position": {"x": -0.28103744983673096, "y": 0.9012410640716553, "z": -1.8205620050430298}, "type": "Pot", "is_goal_object": false}, {"objectName": "Window_3746cf00", "rotation": {"x": 90.0, "y": 6.640798528678715e-05, "z": 0.0}, "position": {"x": 0.5820000171661377, "y": 1.6139999628067017, "z": -1.9670000076293945}, "type": "Window", "is_goal_object": false}, {"objectName": "Window_32eedabf", "rotation": {"x": 90.0, "y": 270.00006103515625, "z": 0.0}, "position": {"x": 1.9699997901916504, "y": 1.5, "z": -0.6159999966621399}, "type": "Window", "is_goal_object": false}, {"objectName": "Spatula_c7c8be6d", "rotation": {"x": 0.14585180580615997, "y": 269.9635925292969, "z": 359.403564453125}, "position": {"x": -2.1406195163726807, "y": 0.9499800801277161, "z": 0.19046877324581146}, "type": "Spatula", "is_goal_object": false}, {"objectName": "PaperTowelRoll_32e76a8a", "rotation": {"x": 0.379329115152359, "y": -0.00552458455786109, "z": 359.9043884277344}, "position": {"x": 1.6718988418579102, "y": 1.0162341594696045, "z": -1.4743974208831787}, "type": "PaperTowelRoll", "is_goal_object": false}, {"objectName": "Microwave_21ff1dc8", "rotation": {"x": 0.10358431935310364, "y": 0.008156775496900082, "z": 0.0015746422577649355}, "position": {"x": -1.0377577543258667, "y": 0.9001288414001465, "z": -1.7230898141860962}, "type": "Microwave", "is_goal_object": false}, {"objectName": "Egg_d489008d", "rotation": {"x": -6.765511352568865e-05, "y": 0.0, "z": 0.0}, "position": {"x": 1.9071784019470215, "y": 0.9370895028114319, "z": 0.540980875492096}, "type": "Egg", "is_goal_object": false}, {"objectName": "Lettuce_23533a35", "rotation": {"x": 359.9612731933594, "y": 0.007574908435344696, "z": 356.5575866699219}, "position": {"x": 1.6680876016616821, "y": 0.9844219088554382, "z": 0.37515905499458313}, "type": "Lettuce", "is_goal_object": false}, {"objectName": "SinkBasin_021423c2", "rotation": {"x": 1.403341910044412e-14, "y": 270.0, "z": 0.0}, "position": {"x": 0.37712618708610535, "y": 0.7658731937408447, "z": -1.6558878421783447}, "type": "SinkBasin", "is_goal_object": false}, {"objectName": "SaltShaker_37e787f6", "rotation": {"x": 359.9811096191406, "y": 89.9943618774414, "z": 0.0022036090958863497}, "position": {"x": -2.1406307220458984, "y": 0.9424319863319397, "z": 0.35319066047668457}, "type": "SaltShaker", "is_goal_object": false}, {"objectName": "CoffeeMachine_1377acc4", "rotation": {"x": -1.2806605809601024e-05, "y": 180.00033569335938, "z": 2.7474322905618465e-07}, "position": {"x": 0.6189999580383301, "y": 0.9000034332275391, "z": 0.5999998450279236}, "type": "CoffeeMachine", "is_goal_object": false}, {"objectName": "PepperShaker_a9510ce3", "rotation": {"x": 359.974853515625, "y": 89.99400329589844, "z": 0.005804228596389294}, "position": {"x": -1.9116418361663818, "y": 0.9424319863319397, "z": 0.3532108664512634}, "type": "PepperShaker", "is_goal_object": false}, {"objectName": "Apple_36134545", "rotation": {"x": -0.0, "y": 0.0, "z": 0.0}, "position": {"x": 1.1671266555786133, "y": 0.97178715467453, "z": -1.4890382289886475}, "type": "Apple", "is_goal_object": false}, {"objectName": "ButterKnife_574df12d", "rotation": {"x": 0.006462879944592714, "y": -0.0024939021095633507, "z": 0.7472374439239502}, "position": {"x": 0.035134948790073395, "y": 0.9140984416007996, "z": 0.292340487241745}, "type": "ButterKnife", "is_goal_object": false}, {"objectName": "StoveKnob_f6a2c6ae", "rotation": {"x": 45.00001907348633, "y": 180.00006103515625, "z": 2.650439512308367e-07}, "position": {"x": 1.246000051498413, "y": 0.9136999845504761, "z": 0.11800000071525574}, "type": "StoveKnob", "is_goal_object": false}, {"objectName": "StoveKnob_83d2b2c6", "rotation": {"x": 45.00001907348633, "y": 180.00006103515625, "z": 2.650439512308367e-07}, "position": {"x": 1.3730000257492065, "y": 0.9136999845504761, "z": 0.11800000071525574}, "type": "StoveKnob", "is_goal_object": false}, {"objectName": "StoveKnob_d1a7f320", "rotation": {"x": 45.00001907348633, "y": 180.00006103515625, "z": 2.650439512308367e-07}, "position": {"x": 0.9950000047683716, "y": 0.9136999845504761, "z": 0.11800000071525574}, "type": "StoveKnob", "is_goal_object": false}, {"objectName": "StoveKnob_522eb1f9", "rotation": {"x": 45.00001907348633, "y": 180.00006103515625, "z": 2.650439512308367e-07}, "position": {"x": 1.1269999742507935, "y": 0.9136999845504761, "z": 0.11800000071525574}, "type": "StoveKnob", "is_goal_object": false}, {"objectName": "Potato_a84a1dc4", "rotation": {"x": -0.0011700618779286742, "y": 89.99507141113281, "z": -0.0005090608610771596}, "position": {"x": -1.9116466045379639, "y": 0.9753934741020203, "z": 0.43458887934684753}, "type": "Potato", "is_goal_object": false}, {"objectName": "Pan_6e38dd34", "rotation": {"x": -0.0015013610245659947, "y": 179.99998474121094, "z": -0.0015251872828230262}, "position": {"x": 1.5355480909347534, "y": 0.8997372388839722, "z": -1.7376806735992432}, "type": "Pan", "is_goal_object": false}, {"objectName": "GarbageCan_fe68ea20", "rotation": {"x": -1.0957142876577564e-05, "y": 90.14015197753906, "z": 3.050576924579218e-05}, "position": {"x": -0.3681739866733551, "y": -0.029397785663604736, "z": 0.5391247868537903}, "type": "GarbageCan", "is_goal_object": false}, {"objectName": "DishSponge_4d1f5a3d", "rotation": {"x": -5.087344561616192e-06, "y": -5.1313487347215414e-05, "z": 0.0006146143423393369}, "position": {"x": 0.16771267354488373, "y": 0.9020911455154419, "z": 0.5409809350967407}, "type": "DishSponge", "is_goal_object": false}, {"objectName": "Spoon_b0e5e554", "rotation": {"x": 0.15920346975326538, "y": 89.96267700195312, "z": 359.4726257324219}, "position": {"x": -2.2551462650299072, "y": 0.9425941705703735, "z": 0.4346020817756653}, "type": "Spoon", "is_goal_object": false}, {"objectName": "Fridge_719d160f", "rotation": {"x": -0.0, "y": 0.0, "z": 0.0}, "position": {"x": -2.134999990463257, "y": 0.0, "z": -1.690999984741211}, "type": "Fridge", "is_goal_object": false}, {"objectName": "Mug_1f4402a2", "rotation": {"x": -8.480711403535679e-05, "y": 5.279713514028117e-05, "z": 0.00011949727922910824}, "position": {"x": -0.09697727113962173, "y": 0.9000009298324585, "z": 0.20945744216442108}, "type": "Mug", "is_goal_object": false}, {"objectName": "Faucet_a6ff5c51", "rotation": {"x": -0.0, "y": 322.52734375, "z": 0.0}, "position": {"x": 0.5842000246047974, "y": 0.9038000106811523, "z": -1.88510000705719}, "type": "Faucet", "is_goal_object": false}, {"objectName": "Stool_49adaeb7", "rotation": {"x": 1.2275506258010864, "y": 280.37982177734375, "z": 359.8797607421875}, "position": {"x": -1.4759589433670044, "y": 0.0005843639373779297, "z": 0.4149756133556366}, "type": "Stool", "is_goal_object": false}, {"objectName": "DiningTable_0221beef", "rotation": {"x": -3.948839730583131e-05, "y": -0.004749749321490526, "z": 2.532866710680537e-05}, "position": {"x": -2.255056858062744, "y": -0.004244983196258545, "z": 0.43210574984550476}, "type": "DiningTable", "is_goal_object": false}]}